setup.cfg
setup.py
paycash_api_client.egg-info/PKG-INFO
paycash_api_client.egg-info/SOURCES.txt
paycash_api_client.egg-info/dependency_links.txt
paycash_api_client.egg-info/pbr.json
paycash_api_client.egg-info/requires.txt
paycash_api_client.egg-info/top_level.txt
paycashapiclient/AccountAsset.py
paycashapiclient/AccountAssetTypes.py
paycashapiclient/AccountBalance.py
paycashapiclient/AccountList.py
paycashapiclient/Address.py
paycashapiclient/BankAsset.py
paycashapiclient/BankList.py
paycashapiclient/CreateAccountReqBody.py
paycashapiclient/CreateBankReqBody.py
paycashapiclient/CreateCreditCardReqBody.py
paycashapiclient/CreateProfileReqBody.py
paycashapiclient/CreditCardAsset.py
paycashapiclient/CreditCardList.py
paycashapiclient/DeactivateUserReqBody.py
paycashapiclient/Debit.py
paycashapiclient/Email.py
paycashapiclient/EmailDetails.py
paycashapiclient/EmailDetailsTypes.py
paycashapiclient/EmailList.py
paycashapiclient/KYC.py
paycashapiclient/KYCDocument.py
paycashapiclient/KYCDocumentList.py
paycashapiclient/KYCStatuses.py
paycashapiclient/KYCTypes.py
paycashapiclient/MeProfile.py
paycashapiclient/Phone.py
paycashapiclient/PhoneList.py
paycashapiclient/PhoneNumberTypes.py
paycashapiclient/Profile.py
paycashapiclient/Transaction.py
paycashapiclient/TransactionDetails.py
paycashapiclient/TransactionList.py
paycashapiclient/TransactionReasons.py
paycashapiclient/TransactionStatuses.py
paycashapiclient/VerifyBankReqBody.py
paycashapiclient/VerifyProfileReqBody.py
paycashapiclient/Work.py
paycashapiclient/__init__.py
paycashapiclient/assets_service.py
paycashapiclient/client.py
paycashapiclient/client_support.py
paycashapiclient/client_utils.py
paycashapiclient/kyc_service.py
paycashapiclient/oauth2_client_oauth_2_0.py
paycashapiclient/profile_service.py
paycashapiclient/transactions_service.py
paycashapiclient/user_service.py