Metadata-Version: 1.1
Name: paycash-api-client
Version: 0.0.8
Summary: Client library for the PayCash API
Home-page: https://github.com/rogerthat-platform/paycash-api-client
Author: Green IT Globe
Author-email: apps@greenitglobe.com
License: Apache 2.0
Keywords: paycash,api,client
Platform: UNKNOWN
Classifier: Programming Language :: Python :: 2.7
Classifier: Environment :: Web Environment
Classifier: Operating System :: OS Independent
Classifier: Programming Language :: Python
Classifier: Topic :: Software Development :: Libraries
Classifier: Development Status :: 5 - Production/Stable
Classifier: Intended Audience :: Developers
Classifier: License :: OSI Approved :: Apache Software License
